{
    "data": [
        {
            "question": "aaq1",
            "a": "aaq1opt1",
            "b": "aaq1opt2",
            "c": "aaq1opt3",
            "d": "aaq1opt4",
            "answer": "c",
            "numAnswer": 4,
            "shapeQuestion": true,
            "explain": "정사각형은 각 단계마다 시계 방향으로 90도 회전합니다"
        },
        {
            "question": "aaq2",
            "a": "aaq2opt1",
            "b": "aaq2opt2",
            "c": "aaq2opt3",
            "d": "aaq2opt4",
            "answer": "d",
            "numAnswer": 4,
            "shapeQuestion": true,
            "explain": "첫 번째 행에서 3번째 모양은 첫 두 모양의 음영 영역을 가지고 있습니다! 따라서 두 번째 행에서는 두 개의 하단 직사각형이 음영 처리됩니다"
        },
        {
            "question": "aaq3",
            "a": "aaq3opt1",
            "b": "aaq3opt2",
            "c": "aaq3opt3",
            "d": "aaq3opt4",
            "answer": "b",
            "numAnswer": 4,
            "shapeQuestion": true,
            "explain": "각 행과 열에서, 세 개의 링 중 각각 하나가 검정색으로 음영 처리됩니다"
        },
        {
            "question": "aaq4",
            "a": "aaq4opt1",
            "b": "aaq4opt2",
            "c": "aaq4opt3",
            "d": "aaq4opt4",
            "answer": "d",
            "numAnswer": 4,
            "shapeQuestion": true,
            "explain": "각 행에서는 화살표가 왼쪽, 오른쪽, 아래쪽의 세 방향으로 가리킵니다. 화살표의 수는 각 행에서 1, 2, 3으로 증가합니다"
        },
        {
            "question": "aaq5",
            "a": "aaq5opt1",
            "b": "aaq5opt2",
            "c": "aaq5opt3",
            "d": "aaq5opt4",
            "answer": "b",
            "numAnswer": 4,
            "shapeQuestion": true,
            "explain": "검정 점은 각 단계마다 한 위치씩 위로 (그런 다음 아래로) 이동합니다"
        },
        {
            "question": "aaq6",
            "a": "aaq6opt1",
            "b": "aaq6opt2",
            "c": "aaq6opt3",
            "d": "aaq6opt4",
            "answer": "d",
            "numAnswer": 4,
            "shapeQuestion": true,
            "explain": "검정 점은 한 단계씩 아래로 이동하며 마지막 단계 이후부터 시작합니다! 하나의 삼각형이 음영 처리되고 음영이 없는 삼각형이 교대로 나타납니다"
        },
        {
            "question": "aaq7",
            "a": "aaq7opt1",
            "b": "aaq7opt2",
            "c": "aaq7opt3",
            "d": "aaq7opt4",
            "answer": "c",
            "numAnswer": 4,
            "shapeQuestion": true,
            "explain": "내부와 외부의 검정 원이 서로 반대 방향으로 위아래로 이동하며, 모서리에 도달하면 사라지고 다시 시작합니다"
        },
        {
            "question": "aaq8",
            "a": "aaq8opt1",
            "b": "aaq8opt2",
            "c": "aaq8opt3",
            "d": "aaq8opt4",
            "answer": "a",
            "numAnswer": 4,
            "shapeQuestion": true,
            "explain": "두 개의 검정 원이 반시계 방향으로 흰 원을 채우고 있지만, 한 단계에서 한 개의 검정 원만 이동합니다"
        },
        {
            "question": "aaq9",
            "a": "aaq9opt1",
            "b": "aaq9opt2",
            "c": "aaq9opt3",
            "d": "aaq9opt4",
            "answer": "b",
            "numAnswer": 4,
            "shapeQuestion": true,
            "explain": "삼각형은 각 단계마다 시계 방향으로 90도 회전하며, 내부와 외부의 원이 번갈아가며 채워지고 비워집니다."
        },
        {
            "question": "aaq10",
            "a": "aaq10opt1",
            "b": "aaq10opt2",
            "c": "aaq10opt3",
            "d": "aaq10opt4",
            "answer": "c",
            "numAnswer": 4,
            "shapeQuestion": true,
            "explain": "첫 번째 행에서 시작하여 삼각형은 2단계 동안 시계 방향으로 90도 회전한 다음, 90도 반시계 방향으로 회전하여 새로운 행을 시작합니다."
        },
        {
            "question": "aaq11",
            "a": "aaq11opt1",
            "b": "aaq11opt2",
            "c": "aaq11opt3",
            "d": "aaq11opt4",
            "answer": "d",
            "numAnswer": 4,
            "shapeQuestion": true,
            "explain": "위에서 아래로 숫자 행을 보면! 9 * 8 = 72! 72 * 8 = 576! 576 * 8 = 4608"
        },
        {
            "question": "aaq12",
            "a": "aaq12opt1",
            "b": "aaq12opt2",
            "c": "aaq12opt3",
            "d": "aaq12opt4",
            "answer": "c",
            "numAnswer": 4,
            "shapeQuestion": true,
            "explain": "흰 점의 수는 매번 1개씩 증가하며, 수직과 수평 모두에서 연결됩니다."
        },
        {
            "question": "aaq13",
            "a": "aaq13opt1",
            "b": "aaq13opt2",
            "c": "aaq13opt3",
            "d": "aaq13opt4",
            "answer": "b",
            "numAnswer": 4,
            "shapeQuestion": true,
            "explain": "가로 줄은 +2, -3, +2로 진행됩니다! 세로 줄은 -3, +2, -3으로 진행됩니다"
        },
        {
            "question": "aaq14",
            "a": "aaq14opt1",
            "b": "aaq14opt2",
            "c": "aaq14opt3",
            "d": "aaq14opt4",
            "answer": "d",
            "numAnswer": 4,
            "shapeQuestion": true,
            "explain": "(8 + 7) * 5 = 76"
        },
        {
            "question": "aaq15",
            "a": "aaq15opt1",
            "b": "aaq15opt2",
            "c": "aaq15opt3",
            "d": "aaq15opt4",
            "answer": "b",
            "numAnswer": 4,
            "shapeQuestion": true,
            "explain": "행과 열에서 처음 세 숫자를 더하여 네 번째 숫자에 도달합니다"
        },
        {
            "question": "aaq16",
            "a": "aaq16opt1",
            "b": "aaq16opt2",
            "c": "aaq16opt3",
            "d": "aaq16opt4",
            "answer": "a",
            "numAnswer": 4,
            "shapeQuestion": true,
            "explain": "각 행과 열에는 다섯 개의 검정 점과 네 개의 흰 점이 포함되어 있습니다"
        },
        {
            "question": "aaq17",
            "a": "aaq17opt1",
            "b": "aaq17opt2",
            "c": "aaq17opt3",
            "d": "aaq17opt4",
            "answer": "b",
            "numAnswer": 4,
            "shapeQuestion": true,
            "explain": "(73 + 25) / 2 = 50"
        },
        {
            "question": "aaq18",
            "a": "aaq18opt1",
            "b": "aaq18opt2",
            "c": "aaq18opt3",
            "d": "aaq18opt4",
            "answer": "d",
            "numAnswer": 4,
            "shapeQuestion": true,
            "explain": "세 개의 첫 번째 정사각형에서 같은 위치에 세 번 나타나는 선만 최종 정사각형으로 전달됩니다"
        },
        {
            "question": "aaq19",
            "a": "aaq19opt1",
            "b": "aaq19opt2",
            "c": "aaq19opt3",
            "d": "aaq19opt4",
            "answer": "d",
            "numAnswer": 4,
            "shapeQuestion": true,
            "explain": "각 호에 대해, 시계 방향으로 1/4 원을 추가합니다"
        },
        {
            "question": "aaq20",
            "a": "aaq20opt1",
            "b": "aaq20opt2",
            "c": "aaq20opt3",
            "d": "aaq20opt4",
            "answer": "a",
            "numAnswer": 4,
            "shapeQuestion": true,
            "explain": "6 * 9 = 54 (가운데 두 블록을 아래에서 읽기)"
        },
        {
            "question": "aaq21",
            "a": "aaq21opt1",
            "b": "aaq21opt2",
            "c": "aaq21opt3",
            "d": "aaq21opt4",
            "answer": "c",
            "numAnswer": 4,
            "shapeQuestion": true,
            "explain": "삼각형을 가로와 세로로 보면 90도 회전합니다"
        },
        {
            "question": "aaq22",
            "a": "aaq22opt1",
            "b": "aaq22opt2",
            "c": "aaq22opt3",
            "d": "aaq22opt4",
            "answer": "c",
            "numAnswer": 4,
            "shapeQuestion": true,
            "explain": "각 숫자는 그리드에서의 위치를 나타냅니다. 55는 5행 5열을 나타냅니다"
        },
        {
            "question": "aaq23",
            "a": "aaq23opt1",
            "b": "aaq23opt2",
            "c": "aaq23opt3",
            "d": "aaq23opt4",
            "answer": "d",
            "numAnswer": 4,
            "shapeQuestion": true,
            "explain": "각 3자리 숫자의 숫자를 더하여 2자리 숫자를 얻습니다"
        },
        {
            "question": "aaq24",
            "a": "aaq24opt1",
            "b": "aaq24opt2",
            "c": "aaq24opt3",
            "d": "aaq24opt4",
            "answer": "c",
            "numAnswer": 4,
            "shapeQuestion": true,
            "explain": "각 행과 열에서 첫 번째 두 정사각형에서 공통된 선만 최종 정사각형으로 전달됩니다"
        },
        {
            "question": "aaq25",
            "a": "aaq25opt1",
            "b": "aaq25opt2",
            "c": "aaq25opt3",
            "d": "aaq25opt4",
            "answer": "a",
            "numAnswer": 4,
            "shapeQuestion": true,
            "explain": "두 번 회전 후, 흰 점과 검정 점 모두 현재 검정 점이 있는 육각형의 가장 낮은 모서리에 위치합니다"
        },
        {
            "question": "aaq26",
            "a": "aaq26opt1",
            "b": "aaq26opt2",
            "c": "aaq26opt3",
            "d": "aaq26opt4",
            "answer": "b",
            "numAnswer": 4,
            "shapeQuestion": true,
            "explain": "내부 육각형은 시계 반대 방향으로 한 면씩 분해되고, 외부 육각형은 시계 방향으로 한 면씩 구성됩니다"
        },
        {
            "question": "aaq27",
            "a": "aaq27opt1",
            "b": "aaq27opt2",
            "c": "aaq27opt3",
            "d": "aaq27opt4",
            "answer": "a",
            "numAnswer": 4,
            "shapeQuestion": true,
            "explain": "42 / 3 = 14! 그리고! 51 / 3 = 17"
        },
        {
            "question": "aaq28",
            "a": "aaq28opt1",
            "b": "aaq28opt2",
            "c": "aaq28opt3",
            "d": "aaq28opt4",
            "answer": "b",
            "numAnswer": 4,
            "shapeQuestion": true,
            "explain": "중심 주위의 숫자는 7씩 증가합니다 (다른 숫자는 각각 3과 5씩 증가합니다)"
        },
        {
            "question": "aaq29",
            "a": "aaq29opt1",
            "b": "aaq29opt2",
            "c": "aaq29opt3",
            "d": "aaq29opt4",
            "answer": "b",
            "numAnswer": 4,
            "shapeQuestion": true,
            "explain": "가로를 보면 외부 원이 제거되고, 세로를 보면 외부 원이 추가됩니다"
        },
        {
            "question": "aaq30",
            "a": "aaq30opt1",
            "b": "aaq30opt2",
            "c": "aaq30opt3",
            "d": "aaq30opt4",
            "answer": "d",
            "numAnswer": 4,
            "shapeQuestion": true,
            "explain": "가로를 보면, 왼쪽 상단 사분면의 점이 반대 코너로 이동하고, 오른쪽 상단 사분면의 점이 각 단계에서 시계 반대 방향으로 하나의 코너 이동하며, 왼쪽 하단 사분면의 점이 상단 두 코너 사이를 이동하고, 오른쪽 하단 사분면의 점이 각 단계에서 시계 방향으로 하나의 코너 이동합니다"
        },
        {
            "question": "aaq31",
            "a": "aaq31opt1",
            "b": "aaq31opt2",
            "c": "aaq31opt3",
            "d": "aaq31opt4",
            "answer": "c",
            "numAnswer": 4,
            "shapeQuestion": true,
            "explain": "가로를 보면 각 행에 3을 추가하고! 세로를 보면 각 열에 2를 추가합니다"
        },
        {
            "question": "aaq32",
            "a": "aaq32opt1",
            "b": "aaq32opt2",
            "c": "aaq32opt3",
            "d": "aaq32opt4",
            "answer": "d",
            "numAnswer": 4,
            "shapeQuestion": true,
            "explain": "왼쪽 상단 코너에서 시작하여 상단 라인을 따라 작업한 다음, 두 번째 라인을 따라 되돌아가며 9를 추가한 다음 3을 빼는 방식으로 작업합니다"
        },
        {
            "question": "aaq33",
            "a": "aaq33opt1",
            "b": "aaq33opt2",
            "c": "aaq33opt3",
            "d": "aaq33opt4",
            "answer": "b",
            "numAnswer": 4,
            "shapeQuestion": true,
            "explain": "(6 + 7) – (4 + 5) = 5"
        },
        {
            "question": "aaq34",
            "a": "aaq34opt1",
            "b": "aaq34opt2",
            "c": "aaq34opt3",
            "d": "aaq34opt4",
            "answer": "c",
            "numAnswer": 4,
            "shapeQuestion": true,
            "explain": "큰 직사각형은 시계 반대 방향으로 한 면씩 분해되고 있습니다! 작은 직사각형은 시계 방향으로 한 면씩 구성되고 있습니다."
        },
        {
            "question": "aaq35",
            "a": "aaq35opt1",
            "b": "aaq35opt2",
            "c": "aaq35opt3",
            "d": "aaq35opt4",
            "answer": "d",
            "numAnswer": 4,
            "shapeQuestion": true,
            "explain": "삼각형, 정사각형, 원의 숫자가 33이 되도록 합니다"
        },
        {
            "question": "aaq36",
            "a": "aaq36opt1",
            "b": "aaq36opt2",
            "c": "aaq36opt3",
            "d": "aaq36opt4",
            "answer": "b",
            "numAnswer": 4,
            "shapeQuestion": true,
            "explain": "가로와 세로를 보면서, 첫 번째 두 정사각형에서 동일한 위치에 나타나는 점만 세 번째 정사각형으로 전달됩니다! 그러나, 이들은 검정에서 흰색으로, 또는 흰색에서 검정으로 변합니다"
        },
        {
            "question": "aaq37",
            "a": "aaq37opt1",
            "b": "aaq37opt2",
            "c": "aaq37opt3",
            "d": "aaq37opt4",
            "answer": "c",
            "numAnswer": 4,
            "shapeQuestion": true,
            "explain": "각 행과 열에서 최종 숫자에 도달하기 위해, 처음 두 숫자를 곱한 후 6으로 나누세요"
        },
        {
            "question": "aaq38",
            "a": "aaq38opt1",
            "b": "aaq38opt2",
            "c": "aaq38opt3",
            "d": "aaq38opt4",
            "answer": "d",
            "numAnswer": 4,
            "shapeQuestion": true,
            "explain": "가로와 세로 모두에서, 첫 번째 두 정사각형 모두에 나타나는 선만 세 번째 정사각형으로 전달됩니다"
        },
        {
            "question": "aaq39",
            "a": "aaq39opt1",
            "b": "aaq39opt2",
            "c": "aaq39opt3",
            "d": "aaq39opt4",
            "answer": "a",
            "numAnswer": 4,
            "shapeQuestion": true,
            "explain": "각 쌍의 원은 서로의 대칭 이미지입니다"
        },
        {
            "question": "aaq40",
            "a": "aaq40opt1",
            "b": "aaq40opt2",
            "c": "aaq40opt3",
            "d": "aaq40opt4",
            "answer": "d",
            "numAnswer": 4,
            "shapeQuestion": true,
            "explain": "6 * 4 = 6 + 18! 7 * 3 = 11 + 10! 9 * 2 = 5 + 13! 그리고! 16 * 4 = 32 + 32"
        },
        {
            "question": "aaq41",
            "a": "aaq41opt1",
            "b": "aaq41opt2",
            "c": "aaq41opt3",
            "d": "aaq41opt4",
            "answer": "d",
            "numAnswer": 4,
            "shapeQuestion": true,
            "explain": "(6 + 8) – 9 = 6"
        },
        {
            "question": "aaq42",
            "a": "aaq42opt1",
            "b": "aaq42opt2",
            "c": "aaq42opt3",
            "d": "aaq42opt4",
            "answer": "a",
            "numAnswer": 4,
            "shapeQuestion": true,
            "explain": "정사각형이 다이아몬드 안으로 들어가고, 다이아몬드는 다시 오각형 안으로 들어가며, 오각형은 바닥에 놓입니다"
        },
        {
            "question": "aaq43",
            "a": "aaq43opt1",
            "b": "aaq43opt2",
            "c": "aaq43opt3",
            "d": "aaq43opt4",
            "answer": "b",
            "numAnswer": 4,
            "shapeQuestion": true,
            "explain": "가로로 볼 때, 점은 각 단계에서 45도 시계 방향으로 이동하지만, 세로로 볼 때는 45도 반시계 방향으로 이동합니다"
        },
        {
            "question": "aaq44",
            "a": "aaq44opt1",
            "b": "aaq44opt2",
            "c": "aaq44opt3",
            "d": "aaq44opt4",
            "answer": "b",
            "numAnswer": 4,
            "shapeQuestion": true,
            "explain": "점은 모서리/면을 반시계 방향으로 이동하며, 직선과 곡선 모두 모서리에서 모서리로 시계 방향으로 이동합니다"
        },
        {
            "question": "aaq45",
            "a": "aaq45opt1",
            "b": "aaq45opt2",
            "c": "aaq45opt3",
            "d": "aaq45opt4",
            "answer": "c",
            "numAnswer": 4,
            "shapeQuestion": true,
            "explain": "왼쪽에서 시작한 직사각형이 각 단계에서 한 번에 하나씩 왼쪽에서 오른쪽으로 이동합니다"
        },
        {
            "question": "aaq46",
            "a": "aaq46opt1",
            "b": "aaq46opt2",
            "c": "aaq46opt3",
            "d": "aaq46opt4",
            "answer": "d",
            "numAnswer": 4,
            "shapeQuestion": true,
            "explain": "가로와 세로를 보면서, 첫 번째 두 정사각형에서 마지막 정사각형으로 선들이 전달되며, 두 개의 선이 첫 번째 두 정사각형에서 같은 위치에 나타나는 경우에는 취소됩니다"
        },
        {
            "question": "aaq47",
            "a": "aaq47opt1",
            "b": "aaq47opt2",
            "c": "aaq47opt3",
            "d": "aaq47opt4",
            "answer": "a",
            "numAnswer": 4,
            "shapeQuestion": true,
            "explain": "13 * 7 = 84!8 + 12 + 7 + 4 = 31"
        },
        {
            "question": "aaq48",
            "a": "aaq48opt1",
            "b": "aaq48opt2",
            "c": "aaq48opt3",
            "d": "aaq48opt4",
            "answer": "b",
            "numAnswer": 4,
            "shapeQuestion": true,
            "explain": "가로로 볼 때, 문자들이 알파벳에서 +2, +3만큼 이동합니다! 예를 들어! AbCdeF! 세로로 볼 때, 문자들은 +4, +5만큼 진행합니다! 예를 들어! AbcdEfghiJ."
        },
        {
            "question": "aaq49",
            "a": "aaq49opt1",
            "b": "aaq49opt2",
            "c": "aaq49opt3",
            "d": "aaq49opt4",
            "answer": "d",
            "numAnswer": 4,
            "shapeQuestion": true,
            "explain": "원은 정사각형이 되고, 네 개의 흰색 정사각형은 흰색 원이 됩니다."
        },
        {
            "question": "aaq50",
            "a": "aaq50opt1",
            "b": "aaq50opt2",
            "c": "aaq50opt3",
            "d": "aaq50opt4",
            "answer": "d",
            "numAnswer": 4,
            "shapeQuestion": true,
            "explain": "가로로 볼 때, 점의 수는 하나씩 증가하고 흰색은 검은색으로 변합니다! 세로로 볼 때, 점의 수는 하나씩 감소하고 점의 색은 동일하게 유지됩니다."
        }
    ]
}
